COPYING
MANIFEST.in
README.rst
requirements-install.txt
requirements.txt
setup.py
tasks.py
lino_cms/__init__.py
lino_cms/setup_info.py
lino_cms.egg-info/PKG-INFO
lino_cms.egg-info/SOURCES.txt
lino_cms.egg-info/dependency_links.txt
lino_cms.egg-info/requires.txt
lino_cms.egg-info/top_level.txt
lino_cms/lib/__init__.py
lino_cms/lib/cal/__init__.py
lino_cms/lib/cal/models.py
lino_cms/lib/cal/fixtures/__init__.py
lino_cms/lib/cal/fixtures/demo2.py
lino_cms/lib/cal/fixtures/std.py
lino_cms/lib/cms/__init__.py
lino_cms/lib/cms/help_texts.py
lino_cms/lib/cms/layouts.py
lino_cms/lib/cms/migrate.py
lino_cms/lib/cms/models.py
lino_cms/lib/cms/settings.py
lino_cms/lib/cms/user_types.py
lino_cms/lib/cms/locale/de/LC_MESSAGES/django.mo
lino_cms/lib/cms/locale/de/LC_MESSAGES/django.po
lino_cms/lib/cms/locale/et/LC_MESSAGES/django.po
lino_cms/lib/cms/locale/fr/LC_MESSAGES/django.po
lino_cms/lib/users/__init__.py
lino_cms/lib/users/models.py
lino_cms/lib/users/ui.py
lino_cms/lib/users/fixtures/__init__.py
lino_cms/lib/users/fixtures/demo.py
lino_cms/lib/users/fixtures/demo2.py
lino_cms/lib/users/fixtures/demo_users.py
tests/__init__.py
tests/test_docs.py
tests/test_packages.py